hypertab/__init__.py
hypertab/hypernetwork.py
hypertab/hypertab.py
hypertab/interfaces.py
hypertab/modules.py
hypertab/training_utils.py
hypertab/mask_design/__init__.py
hypertab/mask_design/feature_selection.py
hypertab-0.6.2.dist-info/METADATA
hypertab-0.6.2.dist-info/WHEEL
hypertab-0.6.2.dist-info/top_level.txt
hypertab-0.6.2.dist-info/RECORD
