Metadata-Version: 2.1
Name: hypertab
Version: 0.6.2
Summary: HyperTab: hypernetwork for small tabular datasets
Home-page: https://github.com/wwydmanski/hypertab
Author: Witold Wydmański
Author-email: wwydmanski@gmail.com
License: MIT
Requires-Dist: numpy (>=1.10.1)
Requires-Dist: python-dotenv (>=0.21.0)
Requires-Dist: scikit-learn (>=0.24.2)
Requires-Dist: setuptools (>=59.8.0)
Requires-Dist: torch
Requires-Dist: torchvision
Requires-Dist: tqdm (>=4.64.0)
